flight_helper/__init__.py
flight_helper/models/__init__.py
flight_helper/models/dto/__init__.py
flight_helper/models/dto/booking.py
flight_helper/models/dto/itinerary.py
flight_helper/models/dto/passenger.py
flight_helper/models/dto/payment.py
flight_helper/models/dto/procurement.py
flight_helper/validator/__init__.py
flight_helper/validator/type_validator.py
python_filght_helper-0.0.1.dist-info/licenses/LICENSE
python_filght_helper-0.0.1.dist-info/METADATA
python_filght_helper-0.0.1.dist-info/WHEEL
python_filght_helper-0.0.1.dist-info/top_level.txt
python_filght_helper-0.0.1.dist-info/RECORD
