Metadata-Version: 2.4
Name: python_filght_helper
Version: 0.0.1
Summary: flight helper python package
Author-email: ckf10000 <ckf10000@sina.com>
License:                                  Apache License
Project-URL: Homepage, https://github.com/ckf10000/python-filght-helper
Project-URL: Source, https://github.com/ckf10000/python-filght-helper
Project-URL: Issues, https://github.com/ckf10000/python-filght-helper/issues
Requires-Python: >=3.12
License-File: LICENSE
Requires-Dist: pydantic==2.12.5
Dynamic: license-file
